pdag/__init__.py
pdag/data_generator.py
pdag/pdag.py
pyPDAG-0.1.1.dist-info/METADATA
pyPDAG-0.1.1.dist-info/WHEEL
pyPDAG-0.1.1.dist-info/top_level.txt
pyPDAG-0.1.1.dist-info/RECORD
